[
    {
        "title": "永恒的边缘解说序",
        "url": "https://xiongod.github.io/sjsbq3/0243.m4a",
        "duration": "",
        "published": "2024-05-23",
        "createTime": "",
        "chapter": 243,
        "id": "bd83a1b0040c4b29932bb561c64056dd"
    },
    {
        "title": "永恒的边缘解说你有一封来自东德情报局的邮件，请查收！",
        "url": "https://xiongod.github.io/sjsbq3/0244.m4a",
        "duration": "",
        "published": "2024-05-23",
        "createTime": "",
        "chapter": 244,
        "id": "1ebce672416b41cc90e4ec04e6f00235"
    },
    {
        "title": "永恒的边缘解说我们在看着你东德秘密警察的日常",
        "url": "https://xiongod.github.io/sjsbq3/0245.m4a",
        "duration": "",
        "published": "2024-05-23",
        "createTime": "",
        "chapter": 245,
        "id": "9fb649b62c5546d8813c34e7d0f92dae"
    },
    {
        "title": "永恒的边缘解说杀死一只知更鸟美国南北方对待黑人的差异",
        "url": "https://xiongod.github.io/sjsbq3/0246.m4a",
        "duration": "",
        "published": "2024-05-23",
        "createTime": "",
        "chapter": 246,
        "id": "3b2dd2e34dbe4dd38b542db82fc84539"
    },
    {
        "title": "永恒的边缘解说柏林好声音西方流行音乐悄然进入东欧",
        "url": "https://xiongod.github.io/sjsbq3/0247.m4a",
        "duration": "",
        "published": "2024-05-23",
        "createTime": "",
        "chapter": 247,
        "id": "c93ca991107d461880c88efd8d33f4b1"
    },
    {
        "title": "永恒的边缘解说自由之行的绿皮书黑人平权运动此起彼伏",
        "url": "https://xiongod.github.io/sjsbq3/0248.m4a",
        "duration": "",
        "published": "2024-05-23",
        "createTime": "",
        "chapter": 248,
        "id": "c99219290f924ea0998f668098822825"
    },
    {
        "title": "永恒的边缘解说狂暴之路K党袭击平权运动者",
        "url": "https://xiongod.github.io/sjsbq3/0249.m4a",
        "duration": "",
        "published": "2024-05-23",
        "createTime": "",
        "chapter": 249,
        "id": "39683f7f069d4338b956020fe0c9cd97"
    },
    {
        "title": "永恒的边缘解说异见者地下出版物的另一种声音",
        "url": "https://xiongod.github.io/sjsbq3/0250.m4a",
        "duration": "",
        "published": "2024-05-23",
        "createTime": "",
        "chapter": 250,
        "id": "eaa80ba081874bd8ae84e7966d285295"
    },
    {
        "title": "永恒的边缘解说漩涡中的赫鲁晓夫苏联政坛暗流涌动",
        "url": "https://xiongod.github.io/sjsbq3/0251.m4a",
        "duration": "",
        "published": "2024-05-23",
        "createTime": "",
        "chapter": 251,
        "id": "b34ea2723ab14fc394d161c3cd77eb4a"
    },
    {
        "title": "永恒的边缘解说风雨哈佛路美国名校的门槛",
        "url": "https://xiongod.github.io/sjsbq3/0252.m4a",
        "duration": "",
        "published": "2024-05-23",
        "createTime": "",
        "chapter": 252,
        "id": "8a4ad1daa0914d609822433a6fc3005e"
    },
    {
        "title": "永恒的边缘解说白宫欢迎你美国司法部首个黑人事务官",
        "url": "https://xiongod.github.io/sjsbq3/0253.m4a",
        "duration": "",
        "published": "2024-05-23",
        "createTime": "",
        "chapter": 253,
        "id": "327ff6ee71254265aaa5cf4e9132072e"
    },
    {
        "title": "永恒的边缘解说莫斯科郊外的晚上维也纳会议后美苏短暂平静",
        "url": "https://xiongod.github.io/sjsbq3/0254.m4a",
        "duration": "",
        "published": "2024-05-23",
        "createTime": "",
        "chapter": 254,
        "id": "e5bed3c509f045859f1e161e91b0045c"
    },
    {
        "title": "永恒的边缘解说杯中窥局美苏博弈层层加码",
        "url": "https://xiongod.github.io/sjsbq3/0255.m4a",
        "duration": "",
        "published": "2024-05-23",
        "createTime": "",
        "chapter": 255,
        "id": "3d2b59b78b1d462b94cfc7ef3c8e853b"
    },
    {
        "title": "永恒的边缘解说职场菜鸟逆袭如何成为总统心腹",
        "url": "https://xiongod.github.io/sjsbq3/0256.m4a",
        "duration": "",
        "published": "2024-05-23",
        "createTime": "",
        "chapter": 256,
        "id": "1e2fb4a607e44a6587268b49ee4e42e8"
    },
    {
        "title": "永恒的边缘解说柏林墙德国被分裂东西欧拉起铁幕",
        "url": "https://xiongod.github.io/sjsbq3/0257.m4a",
        "duration": "",
        "published": "2024-05-23",
        "createTime": "",
        "chapter": 257,
        "id": "b91389e8430b42d39f86f948d98c5392"
    },
    {
        "title": "永恒的边缘解说白宫质问五角大楼你们要在越南复刻猪湾事件",
        "url": "https://xiongod.github.io/sjsbq3/0258.m4a",
        "duration": "",
        "published": "2024-05-23",
        "createTime": "",
        "chapter": 258,
        "id": "07145b803b7741bf87306082111dc34a"
    },
    {
        "title": "永恒的边缘解说FBI要求对马丁路德金的窃听升级为全方位无死角",
        "url": "https://xiongod.github.io/sjsbq3/0259.m4a",
        "duration": "",
        "published": "2024-05-23",
        "createTime": "",
        "chapter": 259,
        "id": "9d78c9ed30e74bac9764bac538007919"
    },
    {
        "title": "永恒的边缘解说那个淡蓝色的卧室",
        "url": "https://xiongod.github.io/sjsbq3/0260.m4a",
        "duration": "",
        "published": "2024-05-23",
        "createTime": "",
        "chapter": 260,
        "id": "6c6f688599a04239880188779043c53d"
    },
    {
        "title": "永恒的边缘解说谈利弊还是谈对错",
        "url": "https://xiongod.github.io/sjsbq3/0261.m4a",
        "duration": "",
        "published": "2024-05-23",
        "createTime": "",
        "chapter": 261,
        "id": "b3257d17beff4e7bab3ff0118bbd4ddb"
    },
    {
        "title": "永恒的边缘解说你好，艾瑟尔女男爵",
        "url": "https://xiongod.github.io/sjsbq3/0262.m4a",
        "duration": "",
        "published": "2024-05-23",
        "createTime": "",
        "chapter": 262,
        "id": "2b94b250cf9a40238f67a32296e6e337"
    },
    {
        "title": "永恒的边缘解说此情可待成追忆",
        "url": "https://xiongod.github.io/sjsbq3/0263.m4a",
        "duration": "",
        "published": "2024-05-23",
        "createTime": "",
        "chapter": 263,
        "id": "86c69dadb7e8404ca30d8bc6cceb76bf"
    },
    {
        "title": "永恒的边缘解说演员的诞生",
        "url": "https://xiongod.github.io/sjsbq3/0264.m4a",
        "duration": "",
        "published": "2024-05-23",
        "createTime": "",
        "chapter": 264,
        "id": "ad094f36c5c54bdf8005b9044a51a7a4"
    },
    {
        "title": "永恒的边缘解说柏林墙以东",
        "url": "https://xiongod.github.io/sjsbq3/0265.m4a",
        "duration": "",
        "published": "2024-05-23",
        "createTime": "",
        "chapter": 265,
        "id": "576d9d68d4464bbeb59cb4aacf1b0e90"
    },
    {
        "title": "永恒的边缘解说猫鼬行动",
        "url": "https://xiongod.github.io/sjsbq3/0266.m4a",
        "duration": "",
        "published": "2024-05-23",
        "createTime": "",
        "chapter": 266,
        "id": "af2bd204208642f79d3ea0e007a90632"
    },
    {
        "title": "永恒的边缘解说莫斯科的纠结卡斯特罗如果不听话，还帮他吗",
        "url": "https://xiongod.github.io/sjsbq3/0267.m4a",
        "duration": "",
        "published": "2024-05-23",
        "createTime": "",
        "chapter": 267,
        "id": "8e292a63f08645daadeac59bf744e923"
    },
    {
        "title": "永恒的边缘解说嘘，保密！",
        "url": "https://xiongod.github.io/sjsbq3/0268.m4a",
        "duration": "",
        "published": "2024-05-23",
        "createTime": "",
        "chapter": 268,
        "id": "c653d7ba2fdf49d69684d104ee0e0001"
    },
    {
        "title": "永恒的边缘解说CIA古巴如果现在发射导弹，分钟后将击中白宫",
        "url": "https://xiongod.github.io/sjsbq3/0269.m4a",
        "duration": "",
        "published": "2024-05-23",
        "createTime": "",
        "chapter": 269,
        "id": "e590070dec4447418d4e93dd329fbad0"
    },
    {
        "title": "永恒的边缘解说苏联国防部建议古巴导弹发射权交给卡斯特罗",
        "url": "https://xiongod.github.io/sjsbq3/0270.m4a",
        "duration": "",
        "published": "2024-05-23",
        "createTime": "",
        "chapter": 270,
        "id": "13aea3a9a08d4a46a588cabc205fa17f"
    },
    {
        "title": "永恒的边缘解说土耳其我们欢迎美方核武入驻",
        "url": "https://xiongod.github.io/sjsbq3/0271.m4a",
        "duration": "",
        "published": "2024-05-23",
        "createTime": "",
        "chapter": 271,
        "id": "edb22f5ec3f649aa8a8224dbbf40b6cc"
    },
    {
        "title": "永恒的边缘解说末日之恋",
        "url": "https://xiongod.github.io/sjsbq3/0272.m4a",
        "duration": "",
        "published": "2024-05-23",
        "createTime": "",
        "chapter": 272,
        "id": "6edef4be40e9427083f5a78d98c09330"
    },
    {
        "title": "永恒的边缘解说美国战略空军警报等级由三级上升为二级",
        "url": "https://xiongod.github.io/sjsbq3/0273.m4a",
        "duration": "",
        "published": "2024-05-23",
        "createTime": "",
        "chapter": 273,
        "id": "d19ad72282544bd98e8495dcb66d3321"
    },
    {
        "title": "永恒的边缘解说赫鲁晓夫建议谈判，拆除在古巴的导弹装置",
        "url": "https://xiongod.github.io/sjsbq3/0274.m4a",
        "duration": "",
        "published": "2024-05-23",
        "createTime": "",
        "chapter": 274,
        "id": "43fc8120ae7f495e93da64645ad81031"
    },
    {
        "title": "永恒的边缘解说如果明天就是末日",
        "url": "https://xiongod.github.io/sjsbq3/0275.m4a",
        "duration": "",
        "published": "2024-05-23",
        "createTime": "",
        "chapter": 275,
        "id": "17e451d6102441aca3fba8075f0d6fa5"
    },
    {
        "title": "永恒的边缘解说谈理想，还是谈务实",
        "url": "https://xiongod.github.io/sjsbq3/0276.m4a",
        "duration": "",
        "published": "2024-05-23",
        "createTime": "",
        "chapter": 276,
        "id": "7f2675bd8b8c412b8420a4979b737ae0"
    },
    {
        "title": "永恒的边缘解说莫斯科下令颗洲际导弹进入发射预备状态",
        "url": "https://xiongod.github.io/sjsbq3/0277.m4a",
        "duration": "",
        "published": "2024-05-23",
        "createTime": "",
        "chapter": 277,
        "id": "6a2bf4a66daa4b92b2c6e66fda217e46"
    },
    {
        "title": "永恒的边缘解说番外篇",
        "url": "https://xiongod.github.io/sjsbq3/0278.m4a",
        "duration": "",
        "published": "2024-05-23",
        "createTime": "",
        "chapter": 278,
        "id": "a42ac071cfd94211ba3e1ecdb502499e"
    },
    {
        "title": "永恒的边缘解说美国传媒业首席评论员建议双方各退一步",
        "url": "https://xiongod.github.io/sjsbq3/0279.m4a",
        "duration": "",
        "published": "2024-05-23",
        "createTime": "",
        "chapter": 279,
        "id": "63a99d181fa341659dcd3a6f59436846"
    },
    {
        "title": "永恒的边缘解说要把核弹发出去，总共分几步",
        "url": "https://xiongod.github.io/sjsbq3/0280.m4a",
        "duration": "",
        "published": "2024-05-23",
        "createTime": "",
        "chapter": 280,
        "id": "d3f2c28712f443869400224929bb6faf"
    },
    {
        "title": "永恒的边缘解说苏联防空导弹在古巴击中美军高空侦察机",
        "url": "https://xiongod.github.io/sjsbq3/0281.m4a",
        "duration": "",
        "published": "2024-05-23",
        "createTime": "",
        "chapter": 281,
        "id": "40a7db0a2f424d059af19e3266493c4b"
    },
    {
        "title": "永恒的边缘解说和平真好",
        "url": "https://xiongod.github.io/sjsbq3/0282.m4a",
        "duration": "",
        "published": "2024-05-23",
        "createTime": "",
        "chapter": 282,
        "id": "992a4f7fbd5440aba147a3f84cac2193"
    },
    {
        "title": "永恒的边缘解说摇滚乐NO！",
        "url": "https://xiongod.github.io/sjsbq3/0283.m4a",
        "duration": "",
        "published": "2024-05-23",
        "createTime": "",
        "chapter": 283,
        "id": "645d68c66dc649d8a66ce58060eac143"
    },
    {
        "title": "永恒的边缘解说叔叔，你能让我过去吗我妈妈在那边等我",
        "url": "https://xiongod.github.io/sjsbq3/0284.m4a",
        "duration": "",
        "published": "2024-05-23",
        "createTime": "",
        "chapter": 284,
        "id": "d59e9c9b13c94172b7e6e5cff600e1c9"
    },
    {
        "title": "永恒的边缘解说这辈子，你有没有为谁拼过命",
        "url": "https://xiongod.github.io/sjsbq3/0285.m4a",
        "duration": "",
        "published": "2024-05-23",
        "createTime": "",
        "chapter": 285,
        "id": "0110449b15714e3a9c7fc064ababbb02"
    },
    {
        "title": "永恒的边缘解说通往自由的通道",
        "url": "https://xiongod.github.io/sjsbq3/0286.m4a",
        "duration": "",
        "published": "2024-05-23",
        "createTime": "",
        "chapter": 286,
        "id": "580dd1b8f59246468cd3e5d9e304ddb9"
    },
    {
        "title": "永恒的边缘解说马丁路德金再等等黑人已经等了年了！",
        "url": "https://xiongod.github.io/sjsbq3/0287.m4a",
        "duration": "",
        "published": "2024-05-23",
        "createTime": "",
        "chapter": 287,
        "id": "62acc4637d9d4902ae24285df0c08ec6"
    },
    {
        "title": "永恒的边缘解说高压水枪和警犬",
        "url": "https://xiongod.github.io/sjsbq3/0288.m4a",
        "duration": "",
        "published": "2024-05-23",
        "createTime": "",
        "chapter": 288,
        "id": "3160ff6848354501b267fd376bf7bbb1"
    },
    {
        "title": "永恒的边缘解说Glory！",
        "url": "https://xiongod.github.io/sjsbq3/0289.m4a",
        "duration": "",
        "published": "2024-05-23",
        "createTime": "",
        "chapter": 289,
        "id": "269c831150ed46569cd0d21c5763093d"
    },
    {
        "title": "永恒的边缘解说州权VS联邦政府权",
        "url": "https://xiongod.github.io/sjsbq3/0290.m4a",
        "duration": "",
        "published": "2024-05-23",
        "createTime": "",
        "chapter": 290,
        "id": "1ca264fb014a41afa940774da92f08c1"
    },
    {
        "title": "永恒的边缘解说趴下！老实点！少废话！",
        "url": "https://xiongod.github.io/sjsbq3/0291.m4a",
        "duration": "",
        "published": "2024-05-23",
        "createTime": "",
        "chapter": 291,
        "id": "84231b10eff2443caa3a4ec07496018b"
    },
    {
        "title": "永恒的边缘解说便宜点开什么玩笑，这可是香奈儿！",
        "url": "https://xiongod.github.io/sjsbq3/0292.m4a",
        "duration": "",
        "published": "2024-05-23",
        "createTime": "",
        "chapter": 292,
        "id": "2541032954cf471c828b99d3560c81c4"
    },
    {
        "title": "永恒的边缘解说你有没有听过一支披头士乐队他们最近好像挺火的",
        "url": "https://xiongod.github.io/sjsbq3/0293.m4a",
        "duration": "",
        "published": "2024-05-23",
        "createTime": "",
        "chapter": 293,
        "id": "31eec3cee60f4dc7b45bc6f38290b29b"
    },
    {
        "title": "永恒的边缘解说燥起来！桃色岁月！",
        "url": "https://xiongod.github.io/sjsbq3/0294.m4a",
        "duration": "",
        "published": "2024-05-23",
        "createTime": "",
        "chapter": 294,
        "id": "b95da67afe8f447084ef2ece2a1b80db"
    },
    {
        "title": "永恒的边缘解说《古拉格群岛》",
        "url": "https://xiongod.github.io/sjsbq3/0295.m4a",
        "duration": "",
        "published": "2024-05-23",
        "createTime": "",
        "chapter": 295,
        "id": "0f0c6d53f6af4654a6dad21d13a0c324"
    },
    {
        "title": "永恒的边缘解说段子里的苏联社会",
        "url": "https://xiongod.github.io/sjsbq3/0296.m4a",
        "duration": "",
        "published": "2024-05-23",
        "createTime": "",
        "chapter": 296,
        "id": "980b57af10cf4fc79b68546dcac78b06"
    },
    {
        "title": "永恒的边缘解说阿拉巴马州州长黑人无权进入大学！",
        "url": "https://xiongod.github.io/sjsbq3/0297.m4a",
        "duration": "",
        "published": "2024-05-23",
        "createTime": "",
        "chapter": 297,
        "id": "307a8246eb844f488b9109a83193a7cc"
    },
    {
        "title": "永恒的边缘解说我的天，越南又怎么了！",
        "url": "https://xiongod.github.io/sjsbq3/0298.m4a",
        "duration": "",
        "published": "2024-05-23",
        "createTime": "",
        "chapter": 298,
        "id": "8f168c1af88e4f17862912b363651be0"
    },
    {
        "title": "永恒的边缘解说柏林墙两侧，美苏坦克对峙",
        "url": "https://xiongod.github.io/sjsbq3/0299.m4a",
        "duration": "",
        "published": "2024-05-23",
        "createTime": "",
        "chapter": 299,
        "id": "464b4e4905694d14a87654db1e09b414"
    },
    {
        "title": "永恒的边缘解说答案在风中飘扬",
        "url": "https://xiongod.github.io/sjsbq3/0300.m4a",
        "duration": "",
        "published": "2024-05-23",
        "createTime": "",
        "chapter": 300,
        "id": "89b6d3b2ccf846b4886255434e088238"
    },
    {
        "title": "永恒的边缘解说乐队的夏天",
        "url": "https://xiongod.github.io/sjsbq3/0301.m4a",
        "duration": "",
        "published": "2024-05-23",
        "createTime": "",
        "chapter": 301,
        "id": "b9b8d8f19eee41c0863a5afa9ab736db"
    },
    {
        "title": "永恒的边缘解说什么！马龙白兰度今天要来",
        "url": "https://xiongod.github.io/sjsbq3/0302.m4a",
        "duration": "",
        "published": "2024-05-23",
        "createTime": "",
        "chapter": 302,
        "id": "289ac984ded549f0955bcca2be64f974"
    },
    {
        "title": "永恒的边缘解说I have a dream",
        "url": "https://xiongod.github.io/sjsbq3/0303.m4a",
        "duration": "",
        "published": "2024-05-23",
        "createTime": "",
        "chapter": 303,
        "id": "d7647edd03f145e78f8151544a306d90"
    },
    {
        "title": "永恒的边缘解说他们在南非抓了很多黑人，其中一个，叫曼德拉",
        "url": "https://xiongod.github.io/sjsbq3/0304.m4a",
        "duration": "",
        "published": "2024-05-23",
        "createTime": "",
        "chapter": 304,
        "id": "64bfc998a71144e48648e24ad93e1dad"
    },
    {
        "title": "永恒的边缘解说也许我们该筹建一个黑人武装，就叫它黑豹吧",
        "url": "https://xiongod.github.io/sjsbq3/0305.m4a",
        "duration": "",
        "published": "2024-05-23",
        "createTime": "",
        "chapter": 305,
        "id": "4fa2c6dbf9c841bc899517e60ed97290"
    },
    {
        "title": "永恒的边缘解说K党胡佛军方鹰派黑帮情敌卡斯特罗",
        "url": "https://xiongod.github.io/sjsbq3/0306.m4a",
        "duration": "",
        "published": "2024-05-23",
        "createTime": "",
        "chapter": 306,
        "id": "de68a0bb84864befb656c1e1c3c51c79"
    },
    {
        "title": "永恒的边缘解说那一秒，这一刻",
        "url": "https://xiongod.github.io/sjsbq3/0307.m4a",
        "duration": "",
        "published": "2024-05-23",
        "createTime": "",
        "chapter": 307,
        "id": "4ea8fc13b8d644068f862397e5df2679"
    },
    {
        "title": "永恒的边缘解说遗愿清单",
        "url": "https://xiongod.github.io/sjsbq3/0308.m4a",
        "duration": "",
        "published": "2024-05-23",
        "createTime": "",
        "chapter": 308,
        "id": "82364fdf09e544b18930a53ee31c940b"
    },
    {
        "title": "永恒的边缘解说林登约翰逊这个德州小子能行吗",
        "url": "https://xiongod.github.io/sjsbq3/0309.m4a",
        "duration": "",
        "published": "2024-05-23",
        "createTime": "",
        "chapter": 309,
        "id": "7a739071036242d6b70d72c645c99abd"
    },
    {
        "title": "永恒的边缘解说男孩要穷养女孩要富养",
        "url": "https://xiongod.github.io/sjsbq3/0310.m4a",
        "duration": "",
        "published": "2024-05-23",
        "createTime": "",
        "chapter": 310,
        "id": "c764b92917c640b894cb8e7c2d51cae3"
    },
    {
        "title": "永恒的边缘解说一曲成名",
        "url": "https://xiongod.github.io/sjsbq3/0311.m4a",
        "duration": "",
        "published": "2024-05-23",
        "createTime": "",
        "chapter": 311,
        "id": "697b63e674c149cca5452a37ecf762fe"
    },
    {
        "title": "永恒的边缘解说贵族学校哪家强",
        "url": "https://xiongod.github.io/sjsbq3/0312.m4a",
        "duration": "",
        "published": "2024-05-23",
        "createTime": "",
        "chapter": 312,
        "id": "6f461ad07dcd45979ea299f0168ab5ad"
    },
    {
        "title": "永恒的边缘解说幸福是什么",
        "url": "https://xiongod.github.io/sjsbq3/0313.m4a",
        "duration": "",
        "published": "2024-05-23",
        "createTime": "",
        "chapter": 313,
        "id": "961f346062cd4281a0eedbb159033b91"
    },
    {
        "title": "永恒的边缘解说勃列日涅夫向赫鲁晓夫同志七十岁生日送上最衷心的祝愿",
        "url": "https://xiongod.github.io/sjsbq3/0314.m4a",
        "duration": "",
        "published": "2024-05-23",
        "createTime": "",
        "chapter": 314,
        "id": "aa57d4a6e5894dd8af81ce1a098a4be3"
    },
    {
        "title": "永恒的边缘解说绿色森林里的别墅",
        "url": "https://xiongod.github.io/sjsbq3/0315.m4a",
        "duration": "",
        "published": "2024-05-23",
        "createTime": "",
        "chapter": 315,
        "id": "f215a5d7affc491b93f5c09e0f71656b"
    },
    {
        "title": "永恒的边缘解说友谊地久天长",
        "url": "https://xiongod.github.io/sjsbq3/0316.m4a",
        "duration": "",
        "published": "2024-05-23",
        "createTime": "",
        "chapter": 316,
        "id": "5a4255851a6f424890eaa8eb6ce3ee5b"
    },
    {
        "title": "永恒的边缘解说一股来自西伯利亚的寒流",
        "url": "https://xiongod.github.io/sjsbq3/0317.m4a",
        "duration": "",
        "published": "2024-05-23",
        "createTime": "",
        "chapter": 317,
        "id": "0981b70ccfc24506a262c7b7caa4397f"
    },
    {
        "title": "永恒的边缘解说穿梭于东西德的神奇大巴",
        "url": "https://xiongod.github.io/sjsbq3/0318.m4a",
        "duration": "",
        "published": "2024-05-23",
        "createTime": "",
        "chapter": 318,
        "id": "fb3f5d981e48405a81ab8ad639e9acb9"
    },
    {
        "title": "永恒的边缘解说Remember me",
        "url": "https://xiongod.github.io/sjsbq3/0319.m4a",
        "duration": "",
        "published": "2024-05-23",
        "createTime": "",
        "chapter": 319,
        "id": "c6f37148ddd74cb9aaf931a83d621e73"
    },
    {
        "title": "永恒的边缘解说那条叫抑郁的黑狗",
        "url": "https://xiongod.github.io/sjsbq3/0320.m4a",
        "duration": "",
        "published": "2024-05-23",
        "createTime": "",
        "chapter": 320,
        "id": "38048a3df14e4c48b1f04016b7fe1820"
    },
    {
        "title": "永恒的边缘解说如果越南从莫斯科得不到他们想要的，他们会不会去找北京",
        "url": "https://xiongod.github.io/sjsbq3/0321.m4a",
        "duration": "",
        "published": "2024-05-23",
        "createTime": "",
        "chapter": 321,
        "id": "9e2b1d688f5b499a93ec7ac9eca61f01"
    },
    {
        "title": "永恒的边缘解说那些曾经被尘封的文字",
        "url": "https://xiongod.github.io/sjsbq3/0322.m4a",
        "duration": "",
        "published": "2024-05-23",
        "createTime": "",
        "chapter": 322,
        "id": "59c25ac2af784cfc82e6259c77d4f03c"
    },
    {
        "title": "永恒的边缘解说番外篇我们终将变成自己年轻时讨厌的样子",
        "url": "https://xiongod.github.io/sjsbq3/0323.m4a",
        "duration": "",
        "published": "2024-05-23",
        "createTime": "",
        "chapter": 323,
        "id": "a7fc12b4dece42fb8b9de2fa48cb64ca"
    },
    {
        "title": "永恒的边缘解说彩虹酒吧",
        "url": "https://xiongod.github.io/sjsbq3/0324.m4a",
        "duration": "",
        "published": "2024-05-23",
        "createTime": "",
        "chapter": 324,
        "id": "b9a58ef126194b9b8f298a885fe5806c"
    },
    {
        "title": "永恒的边缘解说特殊的祭坛",
        "url": "https://xiongod.github.io/sjsbq3/0325.m4a",
        "duration": "",
        "published": "2024-05-23",
        "createTime": "",
        "chapter": 325,
        "id": "7ecfb37857bf4ce58e56d908cf137f7a"
    },
    {
        "title": "永恒的边缘解说新闻的情理法",
        "url": "https://xiongod.github.io/sjsbq3/0326.m4a",
        "duration": "",
        "published": "2024-05-23",
        "createTime": "",
        "chapter": 326,
        "id": "2524f1708ca84d40b5416cd13308ae35"
    },
    {
        "title": "永恒的边缘解说在此特令您加入美利坚合众国武装部队",
        "url": "https://xiongod.github.io/sjsbq3/0327.m4a",
        "duration": "",
        "published": "2024-05-23",
        "createTime": "",
        "chapter": 327,
        "id": "09f72813b11a4014a909009b7d2d88f2"
    },
    {
        "title": "永恒的边缘解说生活的真相",
        "url": "https://xiongod.github.io/sjsbq3/0328.m4a",
        "duration": "",
        "published": "2024-05-23",
        "createTime": "",
        "chapter": 328,
        "id": "5ddd3b24ba0c4480b6a3bd17ebfbe52a"
    },
    {
        "title": "永恒的边缘解说两种别离",
        "url": "https://xiongod.github.io/sjsbq3/0329.m4a",
        "duration": "",
        "published": "2024-05-23",
        "createTime": "",
        "chapter": 329,
        "id": "9d1ddd9fb8a04b94b2d7db9e57248fab"
    },
    {
        "title": "永恒的边缘解说Where are you going",
        "url": "https://xiongod.github.io/sjsbq3/0330.m4a",
        "duration": "",
        "published": "2024-05-23",
        "createTime": "",
        "chapter": 330,
        "id": "d5375c6800894381a085923f142faff5"
    },
    {
        "title": "永恒的边缘解说越战之春季攻势",
        "url": "https://xiongod.github.io/sjsbq3/0331.m4a",
        "duration": "",
        "published": "2024-05-23",
        "createTime": "",
        "chapter": 331,
        "id": "b380e2ad7ee14d8497fc1c439b3e3859"
    },
    {
        "title": "永恒的边缘解说从垮掉的一代到嬉皮士",
        "url": "https://xiongod.github.io/sjsbq3/0332.m4a",
        "duration": "",
        "published": "2024-05-23",
        "createTime": "",
        "chapter": 332,
        "id": "4268e90c99ec45549f198a7a7e1d3ac3"
    },
    {
        "title": "永恒的边缘解说尼克松怎么又是尼克松",
        "url": "https://xiongod.github.io/sjsbq3/0333.m4a",
        "duration": "",
        "published": "2024-05-23",
        "createTime": "",
        "chapter": 333,
        "id": "304aac1004924c1d958b543dbf5e0871"
    },
    {
        "title": "永恒的边缘解说生活的十字路口",
        "url": "https://xiongod.github.io/sjsbq3/0334.m4a",
        "duration": "",
        "published": "2024-05-23",
        "createTime": "",
        "chapter": 334,
        "id": "7da6ae61ee5c4ac1a6f7b745b206f51c"
    },
    {
        "title": "永恒的边缘解说布拉格之春",
        "url": "https://xiongod.github.io/sjsbq3/0335.m4a",
        "duration": "",
        "published": "2024-05-23",
        "createTime": "",
        "chapter": 335,
        "id": "8ca6300f413d4a0dadfd77308dceb9e2"
    },
    {
        "title": "永恒的边缘解说莫斯科的焦虑",
        "url": "https://xiongod.github.io/sjsbq3/0336.m4a",
        "duration": "",
        "published": "2024-05-23",
        "createTime": "",
        "chapter": 336,
        "id": "5836ddcf6b1948debc22e9a7b71d3821"
    },
    {
        "title": "永恒的边缘解说三个人的晚餐",
        "url": "https://xiongod.github.io/sjsbq3/0337.m4a",
        "duration": "",
        "published": "2024-05-23",
        "createTime": "",
        "chapter": 337,
        "id": "b208c48d9e31459295384d6245dfa17b"
    },
    {
        "title": "永恒的边缘解说旧时光，一去不返",
        "url": "https://xiongod.github.io/sjsbq3/0338.m4a",
        "duration": "",
        "published": "2024-05-23",
        "createTime": "",
        "chapter": 338,
        "id": "aa591e72ce5349058860261b8f874aeb"
    },
    {
        "title": "永恒的边缘解说被诅咒的家族",
        "url": "https://xiongod.github.io/sjsbq3/0339.m4a",
        "duration": "",
        "published": "2024-05-23",
        "createTime": "",
        "chapter": 339,
        "id": "960dfd5ef08b4a658a771ddf632f67e3"
    },
    {
        "title": "永恒的边缘解说生命不能承受之轻",
        "url": "https://xiongod.github.io/sjsbq3/0340.m4a",
        "duration": "",
        "published": "2024-05-23",
        "createTime": "",
        "chapter": 340,
        "id": "005b237c777a4c6ebefea1bef0787405"
    },
    {
        "title": "永恒的边缘解说你好，七零年代",
        "url": "https://xiongod.github.io/sjsbq3/0341.m4a",
        "duration": "",
        "published": "2024-05-23",
        "createTime": "",
        "chapter": 341,
        "id": "14cd0e2163204472b2bb4e90cd41718f"
    },
    {
        "title": "永恒的边缘解说番外篇课后作业精彩留言赏析",
        "url": "https://xiongod.github.io/sjsbq3/0342.m4a",
        "duration": "",
        "published": "2024-05-23",
        "createTime": "",
        "chapter": 342,
        "id": "2e44bf5f7e164226b6e2dc848c94e101"
    },
    {
        "title": "永恒的边缘解说有内鬼，终止交易",
        "url": "https://xiongod.github.io/sjsbq3/0343.m4a",
        "duration": "",
        "published": "2024-05-23",
        "createTime": "",
        "chapter": 343,
        "id": "b2270c21d6924cd88c653b7609f5173f"
    },
    {
        "title": "永恒的边缘解说窃听风暴",
        "url": "https://xiongod.github.io/sjsbq3/0344.m4a",
        "duration": "",
        "published": "2024-05-23",
        "createTime": "",
        "chapter": 344,
        "id": "e34b0d5b5eda421f990b8fbbac681275"
    },
    {
        "title": "永恒的边缘解说梦中人",
        "url": "https://xiongod.github.io/sjsbq3/0345.m4a",
        "duration": "",
        "published": "2024-05-23",
        "createTime": "",
        "chapter": 345,
        "id": "a427bb93bb094071a453cc7caf417b48"
    },
    {
        "title": "永恒的边缘解说尼克松年访问北京和莫斯科",
        "url": "https://xiongod.github.io/sjsbq3/0346.m4a",
        "duration": "",
        "published": "2024-05-23",
        "createTime": "",
        "chapter": 346,
        "id": "2971af681e9a433d9a0cc5bbbc6de69a"
    },
    {
        "title": "永恒的边缘解说水门事件",
        "url": "https://xiongod.github.io/sjsbq3/0347.m4a",
        "duration": "",
        "published": "2024-05-23",
        "createTime": "",
        "chapter": 347,
        "id": "59f1f69880ab41068cb5a9fc11006e6e"
    },
    {
        "title": "永恒的边缘解说与生命有关",
        "url": "https://xiongod.github.io/sjsbq3/0348.m4a",
        "duration": "",
        "published": "2024-05-23",
        "createTime": "",
        "chapter": 348,
        "id": "6eb1678a211a421a9ba327a344d9d116"
    },
    {
        "title": "永恒的边缘解说我赦免你的罪",
        "url": "https://xiongod.github.io/sjsbq3/0349.m4a",
        "duration": "",
        "published": "2024-05-23",
        "createTime": "",
        "chapter": 349,
        "id": "28d3f232c3ee4caf875b1d09bf2c1f5d"
    },
    {
        "title": "永恒的边缘解说渡尽劫波兄弟在",
        "url": "https://xiongod.github.io/sjsbq3/0350.m4a",
        "duration": "",
        "published": "2024-05-23",
        "createTime": "",
        "chapter": 350,
        "id": "8344b14acf5840ecaace619de9aee6b6"
    },
    {
        "title": "永恒的边缘解说部里新来个年轻人，叫戈尔巴乔夫",
        "url": "https://xiongod.github.io/sjsbq3/0351.m4a",
        "duration": "",
        "published": "2024-05-23",
        "createTime": "",
        "chapter": 351,
        "id": "804a4e249b37468ea6779942429cdf66"
    },
    {
        "title": "永恒的边缘解说一个CIA特工的枯燥生活",
        "url": "https://xiongod.github.io/sjsbq3/0352.m4a",
        "duration": "",
        "published": "2024-05-23",
        "createTime": "",
        "chapter": 352,
        "id": "c9ac45462f19484fbac7c738cb7b1b9b"
    },
    {
        "title": "永恒的边缘解说是墙的错",
        "url": "https://xiongod.github.io/sjsbq3/0353.m4a",
        "duration": "",
        "published": "2024-05-23",
        "createTime": "",
        "chapter": 353,
        "id": "ae57eb80ac994c51945a5d990fc1063c"
    },
    {
        "title": "永恒的边缘解说波兰的波澜",
        "url": "https://xiongod.github.io/sjsbq3/0354.m4a",
        "duration": "",
        "published": "2024-05-23",
        "createTime": "",
        "chapter": 354,
        "id": "ac2e0ccf1e2a4852b40e009ad2cd5b85"
    },
    {
        "title": "永恒的边缘解说王牌贱谍养成记",
        "url": "https://xiongod.github.io/sjsbq3/0355.m4a",
        "duration": "",
        "published": "2024-05-23",
        "createTime": "",
        "chapter": 355,
        "id": "c5aeaafbba3f4a8b8daca9734144f909"
    },
    {
        "title": "永恒的边缘解说里根和他的星球大战计划",
        "url": "https://xiongod.github.io/sjsbq3/0356.m4a",
        "duration": "",
        "published": "2024-05-23",
        "createTime": "",
        "chapter": 356,
        "id": "7ae889fd2e644902b0580ae1e184a698"
    },
    {
        "title": "永恒的边缘解说戈尔巴乔夫要接班",
        "url": "https://xiongod.github.io/sjsbq3/0357.m4a",
        "duration": "",
        "published": "2024-05-23",
        "createTime": "",
        "chapter": 357,
        "id": "5d95a1c8315143d99d467d76354e3410"
    },
    {
        "title": "永恒的边缘解说淑女与名媛",
        "url": "https://xiongod.github.io/sjsbq3/0358.m4a",
        "duration": "",
        "published": "2024-05-23",
        "createTime": "",
        "chapter": 358,
        "id": "af812b8d5e944d969f38ca44c1073c80"
    },
    {
        "title": "永恒的边缘解说冷战里的中年危机",
        "url": "https://xiongod.github.io/sjsbq3/0359.m4a",
        "duration": "",
        "published": "2024-05-23",
        "createTime": "",
        "chapter": 359,
        "id": "2ab5d2baf8bb4ab7a36b988aa04f3807"
    },
    {
        "title": "永恒的边缘解说布达佩斯的悸动",
        "url": "https://xiongod.github.io/sjsbq3/0360.m4a",
        "duration": "",
        "published": "2024-05-23",
        "createTime": "",
        "chapter": 360,
        "id": "ef535a9b44634786a072a23cdf88cd72"
    },
    {
        "title": "永恒的边缘解说摇滚撼动柏林墙",
        "url": "https://xiongod.github.io/sjsbq3/0361.m4a",
        "duration": "",
        "published": "2024-05-23",
        "createTime": "",
        "chapter": 361,
        "id": "0d1befd1e2524217b2ed68d3a7ce189d"
    },
    {
        "title": "永恒的边缘解说中东迷局",
        "url": "https://xiongod.github.io/sjsbq3/0362.m4a",
        "duration": "",
        "published": "2024-05-23",
        "createTime": "",
        "chapter": 362,
        "id": "550bdc8c256346fb8ce88089117e1594"
    },
    {
        "title": "永恒的边缘解说以退为进",
        "url": "https://xiongod.github.io/sjsbq3/0363.m4a",
        "duration": "",
        "published": "2024-05-23",
        "createTime": "",
        "chapter": 363,
        "id": "1ca8ac6197dd40c6a4419773a8fe2d4a"
    },
    {
        "title": "永恒的边缘解说切尔诺贝利",
        "url": "https://xiongod.github.io/sjsbq3/0364.m4a",
        "duration": "",
        "published": "2024-05-23",
        "createTime": "",
        "chapter": 364,
        "id": "f18d959b4c974889823da2dfe6d4676b"
    },
    {
        "title": "永恒的边缘解说东欧剧变",
        "url": "https://xiongod.github.io/sjsbq3/0365.m4a",
        "duration": "",
        "published": "2024-05-23",
        "createTime": "",
        "chapter": 365,
        "id": "59cbf2124f504438b7a2015805eea30a"
    },
    {
        "title": "永恒的边缘解说肖普朗小镇的欧洲野餐会",
        "url": "https://xiongod.github.io/sjsbq3/0366.m4a",
        "duration": "",
        "published": "2024-05-23",
        "createTime": "",
        "chapter": 366,
        "id": "8bfe0435cd00408fadd0f9f1ebeb296f"
    },
    {
        "title": "永恒的边缘解说再次爱",
        "url": "https://xiongod.github.io/sjsbq3/0367.m4a",
        "duration": "",
        "published": "2024-05-23",
        "createTime": "",
        "chapter": 367,
        "id": "6b8d3a61524b41528e848e84ca5b1bca"
    },
    {
        "title": "永恒的边缘解说那棵挂满了钥匙串的松树",
        "url": "https://xiongod.github.io/sjsbq3/0368.m4a",
        "duration": "",
        "published": "2024-05-23",
        "createTime": "",
        "chapter": 368,
        "id": "b0ea3d4808944e0b8672b69d0cef237b"
    },
    {
        "title": "永恒的边缘解说笔给你，你来写",
        "url": "https://xiongod.github.io/sjsbq3/0369.m4a",
        "duration": "",
        "published": "2024-05-23",
        "createTime": "",
        "chapter": 369,
        "id": "92f93ad5b4374978bd24387b47cd05ea"
    },
    {
        "title": "永恒的边缘解说大结局",
        "url": "https://xiongod.github.io/sjsbq3/0370.m4a",
        "duration": "",
        "published": "2024-05-23",
        "createTime": "",
        "chapter": 370,
        "id": "21fe5794c3534ceab870ba760ff1776f"
    },
    {
        "title": "中世纪三部曲上新发刊词",
        "url": "https://xiongod.github.io/sjsbq3/0371.m4a",
        "duration": "",
        "published": "2024-05-23",
        "createTime": "",
        "chapter": 371,
        "id": "4f95e3ecf95c4186a76bbb153081ae88"
    },
    {
        "title": "新书上架从西罗马灭亡到文艺复兴（请搜索中世纪三部曲听完整版）",
        "url": "https://xiongod.github.io/sjsbq3/0372.m4a",
        "duration": "",
        "published": "2024-05-23",
        "createTime": "",
        "chapter": 372,
        "id": "38496fb3c3144066a5ac17946eec4e03"
    },
    {
        "title": "新书上架诅咒（上）（天亮版人文通识故事篇已上线）",
        "url": "https://xiongod.github.io/sjsbq3/0373.m4a",
        "duration": "",
        "published": "2024-05-23",
        "createTime": "",
        "chapter": 373,
        "id": "2ef4832fc34947b890d68b58fbec7b34"
    },
    {
        "title": "新书上架诅咒（下）（天亮版人文通识故事篇已上线）",
        "url": "https://xiongod.github.io/sjsbq3/0374.m4a",
        "duration": "",
        "published": "2024-05-23",
        "createTime": "",
        "chapter": 374,
        "id": "7d78eebc06ac4bf9a23bc30db9e78a2a"
    },
    {
        "title": "番外篇（上） 听见内心的力量",
        "url": "https://xiongod.github.io/sjsbq3/0375.m4a",
        "duration": "",
        "published": "2024-05-23",
        "createTime": "",
        "chapter": 375,
        "id": "924aec0b82c042b3822c64f30dcd236e"
    },
    {
        "title": "番外篇（中） 黑天鹅和灰犀牛",
        "url": "https://xiongod.github.io/sjsbq3/0376.m4a",
        "duration": "",
        "published": "2024-05-23",
        "createTime": "",
        "chapter": 376,
        "id": "25d0e424acec4a909bf95f06a1f7379d"
    },
    {
        "title": "番外篇（下） 科学 理性 人文",
        "url": "https://xiongod.github.io/sjsbq3/0377.m4a",
        "duration": "",
        "published": "2024-05-23",
        "createTime": "",
        "chapter": 377,
        "id": "a4fbc22fb66f458e867302461dddd557"
    },
    {
        "title": "中世纪三部曲番外篇（上） 汤姆的恍惚",
        "url": "https://xiongod.github.io/sjsbq3/0378.m4a",
        "duration": "",
        "published": "2024-05-23",
        "createTime": "",
        "chapter": 378,
        "id": "b9749226936f4a38b22de183e3891207"
    },
    {
        "title": "中世纪三部曲番外篇（下） 菲利普的救赎",
        "url": "https://xiongod.github.io/sjsbq3/0379.m4a",
        "duration": "",
        "published": "2024-05-23",
        "createTime": "",
        "chapter": 379,
        "id": "c31a0e6724804aaaaec48b84521e68d8"
    }
]
